achso/__init__.py
achso/controller.py
achso/exception.py
achso/commands/__init__.py
achso/commands/languages.py
achso/commands/sample.py
achso/commands/submissions.py
achso/commands/submit.py
achso/commands/tasks.py
achso/commands/test.py
achso-0.0.2.dist-info/LICENSE
achso-0.0.2.dist-info/METADATA
achso-0.0.2.dist-info/WHEEL
achso-0.0.2.dist-info/entry_points.txt
achso-0.0.2.dist-info/top_level.txt
achso-0.0.2.dist-info/RECORD
