Metadata-Version: 2.1
Name: achso
Version: 0.0.2
Summary: AtCoder Helper Suite
Home-page: https://github.com/kissge/achso
Author: Yuto Kisuge
Author-email: mail@yo.eki.do
License: MIT
Keywords: AtCoder
Platform: UNKNOWN
Classifier: Development Status :: 1 - Planning
Classifier: Topic :: Utilities
Classifier: License :: OSI Approved :: MIT License
Classifier: Programming Language :: Python :: 2
Classifier: Programming Language :: Python :: 2.7
Classifier: Programming Language :: Python :: 3
Classifier: Programming Language :: Python :: 3.4
Classifier: Programming Language :: Python :: 3.5
Requires-Dist: cement (<3)
Requires-Dist: requests
Requires-Dist: lxml
Requires-Dist: cssselect
